{
  "watchList": [
    {
      "vote_count": 1952,
      "id": 348350,
      "video": false,
      "vote_average": 6.7,
      "title": "Solo: A Star Wars Story",
      "popularity": 201.852,
      "poster_path": "https://image.tmdb.org/t/p/w500/3IGbjc5ZC5yxim5W0sFING2kdcz.jpg",
      "original_language": "en",
      "original_title": "Solo: A Star Wars Story",
      "genre_ids": [
        28,
        12,
        878
      ],
      "backdrop_path": "/96B1qMN9RxrAFu6uikwFhQ6N6J9.jpg",
      "adult": false,
      "overview": "Through a series of daring escapades deep within a dark and dangerous criminal underworld, Han Solo meets his mighty future copilot Chewbacca and encounters the notorious gambler Lando Calrissian.",
      "release_date": "2018-05-15"
    },
    {
      "vote_count": 8419,
      "id": 299536,
      "video": false,
      "vote_average": 8.3,
      "title": "Avengers: Infinity War",
      "popularity": 155.869,
      "poster_path": "https://image.tmdb.org/t/p/w500/7WsyChQLEftFiDOVTGkv3hFpyyt.jpg",
      "original_language": "en",
      "original_title": "Avengers: Infinity War",
      "genre_ids": [
        12,
        878,
        28
      ],
      "backdrop_path": "/lmZFxXgJE3vgrciwuDib0N8CfQo.jpg",
      "adult": false,
      "overview": "As the Avengers and their allies have continued to protect the world from threats too large for any one hero to handle, a new danger has emerged from the cosmic shadows: Thanos. A despot of intergalactic infamy, his goal is to collect all six Infinity Stones, artifacts of unimaginable power, and use them to inflict his twisted will on all of reality. Everything the Avengers have fought for has led up to this moment - the fate of Earth and existence itself has never been more uncertain.",
      "release_date": "2018-04-25"
    },
    {
      "vote_count": 12693,
      "id": 680,
      "video": false,
      "vote_average": 8.4,
      "title": "Pulp Fiction",
      "popularity": 23.625,
      "poster_path": "https://image.tmdb.org/t/p/w500/dM2w364MScsjFf8pfMbaWUcWrR.jpg",
      "original_language": "en",
      "original_title": "Pulp Fiction",
      "genre_ids": [
        53,
        80
      ],
      "backdrop_path": "/4cDFJr4HnXN5AdPw4AKrmLlMWdO.jpg",
      "adult": false,
      "overview": "A burger-loving hit man, his philosophical partner, a drug-addled gangster's moll and a washed-up boxer converge in this sprawling, comedic crime caper. Their adventures unfurl in three stories that ingeniously trip back and forth in time.",
      "release_date": "1994-09-10"
    },
    {
      "vote_count": 5901,
      "id": 637,
      "video": false,
      "vote_average": 8.4,
      "title": "Life Is Beautiful",
      "popularity": 14.967,
      "poster_path": "https://image.tmdb.org/t/p/w500/f7DImXDebOs148U4uPjI61iDvaK.jpg",
      "original_language": "it",
      "original_title": "La vita è bella",
      "genre_ids": [
        35,
        18
      ],
      "backdrop_path": "/bORe0eI72D874TMawOOFvqWS6Xe.jpg",
      "adult": false,
      "overview": "A touching story of an Italian book seller of Jewish ancestry who lives in his own little fairy tale. His creative and happy life would come to an abrupt halt when his entire family is deported to a concentration camp during World War II. While locked up he tries to convince his son that the whole thing is just a game.",
      "release_date": "1997-12-20"
    },
    {
      "vote_count": 11126,
      "id": 278,
      "video": false,
      "vote_average": 8.6,
      "title": "The Shawshank Redemption",
      "popularity": 25.45,
      "poster_path": "https://image.tmdb.org/t/p/w500/9O7gLzmreU0nGkIB6K3BsJbzvNv.jpg",
      "original_language": "en",
      "original_title": "The Shawshank Redemption",
      "genre_ids": [
        18,
        80
      ],
      "backdrop_path": "/j9XKiZrVeViAixVRzCta7h1VU9W.jpg",
      "adult": false,
      "overview": "Framed in the 1940s for the double murder of his wife and her lover, upstanding banker Andy Dufresne begins a new life at the Shawshank prison, where he puts his accounting skills to work for an amoral warden. During his long stretch in prison, Dufresne comes to be admired by the other inmates -- including an older prisoner named Red -- for his integrity and unquenchable sense of hope.",
      "release_date": "1994-09-23"
    }
  ]
}